cs_jupyterlab_git/__init__.py
cs_jupyterlab_git/_version.py
cs_jupyterlab_git/git.py
cs_jupyterlab_git/handlers.py
cs_jupyterlab_git/log.py
cs_jupyterlab_git/labextension/build_log.json
cs_jupyterlab_git/labextension/package.json
cs_jupyterlab_git/labextension/schemas/@cs-jupyterlab/git/package.json.orig
cs_jupyterlab_git/labextension/schemas/@cs-jupyterlab/git/plugin.json
cs_jupyterlab_git/labextension/static/lib_index_js-webpack_sharing_consume_default_codemirror_language-webpack_sharing_consume_defa-fc4736.685bceb56b852e5d8ee3.js
cs_jupyterlab_git/labextension/static/lib_index_js-webpack_sharing_consume_default_codemirror_language-webpack_sharing_consume_defa-fc4736.685bceb56b852e5d8ee3.js.map
cs_jupyterlab_git/labextension/static/node_modules_babel_runtime_helpers_esm_assertThisInitialized_js-node_modules_babel_runtime_he-384a07.5c552248d10c5c457bbe.js
cs_jupyterlab_git/labextension/static/node_modules_babel_runtime_helpers_esm_assertThisInitialized_js-node_modules_babel_runtime_he-384a07.5c552248d10c5c457bbe.js.map
cs_jupyterlab_git/labextension/static/node_modules_babel_runtime_helpers_esm_extends_js-node_modules_emotion_memoize_dist_emotion-m-27ec560.96f8b9c6aeaa149e7dd5.js
cs_jupyterlab_git/labextension/static/node_modules_babel_runtime_helpers_esm_extends_js-node_modules_emotion_memoize_dist_emotion-m-27ec560.96f8b9c6aeaa149e7dd5.js.map
cs_jupyterlab_git/labextension/static/node_modules_babel_runtime_helpers_esm_extends_js-node_modules_emotion_memoize_dist_emotion-m-27ec561.c5c3ab5e5097cc24c9b3.js
cs_jupyterlab_git/labextension/static/node_modules_babel_runtime_helpers_esm_extends_js-node_modules_emotion_memoize_dist_emotion-m-27ec561.c5c3ab5e5097cc24c9b3.js.map
cs_jupyterlab_git/labextension/static/node_modules_codemirror_legacy-modes_mode_stex_js.d24afeaa331f71ccc89e.js
cs_jupyterlab_git/labextension/static/node_modules_codemirror_legacy-modes_mode_stex_js.d24afeaa331f71ccc89e.js.map
cs_jupyterlab_git-0.0.3.dist-info/METADATA
cs_jupyterlab_git-0.0.3.dist-info/WHEEL
cs_jupyterlab_git-0.0.3.dist-info/licenses/LICENSE
cs_jupyterlab_git-0.0.3.dist-info/RECORD
